spanum/__init__.py
spanum/numbers_to_words.py
spanum/words_to_numbers.py
spanum-0.0.2.dist-info/METADATA
spanum-0.0.2.dist-info/WHEEL
spanum-0.0.2.dist-info/RECORD
