Metadata-Version: 2.4
Name: spanum
Version: 0.0.2
Summary: Python module that converts numbers to Spanish numerals and vice versa.
Project-URL: Homepage, https://github.com/marydrobotun/spanum
Project-URL: Documentation, https://spanum.readthedocs.io/en/latest
Project-URL: Repository, https://github.com/marydrobotun/spanum
Author-email: Mary Drobotun <marydrobotun@gmail.com>
Maintainer-email: Mary Drobotun <marydrobotun@gmail.com>
License-Expression: MIT
Keywords: numbers,numerals,spanish
Classifier: Development Status :: 4 - Beta
Classifier: Programming Language :: Python
Requires-Python: >=3.10
